flask_sqlalchemy_unchained/__init__.py
flask_sqlalchemy_unchained/py.typed
flask_sqlalchemy_unchained-0.8.0.dist-info/LICENSE
flask_sqlalchemy_unchained-0.8.0.dist-info/METADATA
flask_sqlalchemy_unchained-0.8.0.dist-info/WHEEL
flask_sqlalchemy_unchained-0.8.0.dist-info/RECORD
