Metadata-Version: 2.1
Name: flask-sqlalchemy-unchained
Version: 0.8.0
Summary: Integrates SQLAlchemy Unchained with Flask
License: MIT
Author: Brian Cappello
Author-email: briancappello@gmail.com
Requires-Python: >=3.10,<4.0
Classifier: License :: OSI Approved :: MIT License
Classifier: Programming Language :: Python :: 3
Classifier: Programming Language :: Python :: 3.10
Classifier: Programming Language :: Python :: 3.11
Classifier: Programming Language :: Python :: 3.12
Requires-Dist: flask-sqlalchemy (>=3.0.0,<4.0.0)
Requires-Dist: sqlalchemy-unchained (>=0.14.0,<0.15.0)
